flask_wow/__init__.py
flask_wow/cli.py
flask_wow/templates/app_tmp/app_name/__init__.py
flask_wow/templates/app_tmp/app_name/models.py
flask_wow/templates/app_tmp/app_name/views.py
flask_wow/templates/project_tmp/proj_name/__init__.py
flask_wow/templates/project_tmp/proj_name/config.py
flask_wow/templates/project_tmp/proj_name/handlers.py
flask_wow/templates/project_tmp/proj_name/requirements.txt
flask_wow/templates/project_tmp/proj_name/run.py
flask_wow/templates/project_tmp/proj_name/wsgi.py
flask_wow/templates/project_tmp/proj_name/apps/__init__.py
flask_wow/templates/project_tmp/proj_name/utils/__init__.py
flask_wow-0.2.1.dist-info/LICENSE.rts
flask_wow-0.2.1.dist-info/METADATA
flask_wow-0.2.1.dist-info/WHEEL
flask_wow-0.2.1.dist-info/entry_points.txt
flask_wow-0.2.1.dist-info/top_level.txt
flask_wow-0.2.1.dist-info/RECORD
