Metadata-Version: 2.1
Name: flask-wow
Version: 0.2.1
Summary: A simple CLI Generator for flask apps.
Home-page: https://github.com/ganquan881205/flask-wow.git
Author: Cove
Author-email: cove@happyeyez.com
License: BSD-3-Clause
Keywords: extension flask flask-extension flask-build-tool flask_now flask-now app-generator flask-app-generator app generator
Platform: any
Classifier: Environment :: Web Environment
Classifier: Intended Audience :: Developers
Classifier: License :: OSI Approved :: BSD License
Classifier: Operating System :: OS Independent
Classifier: Programming Language :: Python :: 3 :: Only
Classifier: Framework :: Flask
Classifier: Development Status :: 3 - Alpha
Classifier: Topic :: Utilities
Requires-Python: >=3.6
Requires-Dist: flask (>=1.0.2)
Requires-Dist: click (>=7.0)
